{
  "entrypoints": [
    "main"
  ],
  "origins": {
    "16": [
      13,
      85,
      89,
      103,
      195,
      277,
      514,
      532,
      592,
      608,
      610,
      743,
      16
    ],
    "277": [
      16,
      85,
      89,
      103,
      514,
      532,
      592,
      610,
      277
    ],
    "608": [
      16,
      532,
      592,
      608
    ],
    "17896441": [
      532,
      592,
      918
    ],
    "main": [
      303,
      532,
      179
    ],
    "runtime~main": [
      179,
      532,
      303
    ],
    "01a85c17": [
      16,
      532,
      592,
      13
    ],
    "0e384e19": [
      592,
      671
    ],
    "1be78505": [
      16,
      277,
      532,
      592,
      608
    ],
    "1f391b9e": [
      16,
      277,
      532,
      592,
      85
    ],
    "2868cdab": [
      592,
      61
    ],
    "32dd35a8": [
      592,
      83
    ],
    "3570154c": [
      592,
      707
    ],
    "393be207": [
      592,
      414
    ],
    "3f722a97": [
      639
    ],
    "4ad2bd8b": [
      543
    ],
    "5c2d8334": [
      592,
      226
    ],
    "6875c492": [
      16,
      277,
      532,
      592,
      610
    ],
    "7199ad53": [
      26
    ],
    "814f3328": [
      535
    ],
    "8c484570": [
      676
    ],
    "8e9f0a8a": [
      592,
      35
    ],
    "935f2afb": [
      53
    ],
    "a0632b58": [
      869
    ],
    "a6aa9e1f": [
      16,
      277,
      532,
      592,
      89
    ],
    "ab8db3b5": [
      447
    ],
    "af172acd": [
      592,
      449
    ],
    "b99c8c1f": [
      592,
      151
    ],
    "bdd709f1": [
      592,
      694
    ],
    "c4f5d8e4": [
      16,
      532,
      592,
      195
    ],
    "c890ceb5": [
      246
    ],
    "ccc49370": [
      16,
      277,
      532,
      592,
      103
    ],
    "d610846f": [
      592,
      176
    ],
    "e268232c": [
      80
    ],
    "f05443a6": [
      592,
      264
    ],
    "f8551aab": [
      16,
      532,
      592,
      743
    ],
    "styles": [
      13,
      16,
      85,
      89,
      103,
      179,
      195,
      277,
      303,
      514,
      592,
      608,
      610,
      743,
      918,
      532
    ],
    "common": [
      13,
      16,
      35,
      61,
      83,
      85,
      89,
      103,
      151,
      176,
      195,
      226,
      264,
      277,
      414,
      449,
      514,
      532,
      608,
      610,
      671,
      694,
      707,
      743,
      918,
      592
    ]
  },
  "assets": {
    "13": {
      "js": [
        {
          "file": "assets/js/01a85c17.74644f69.js",
          "hash": "b77cf5538f72f279a34e",
          "publicPath": "/site/assets/js/01a85c17.74644f69.js"
        }
      ]
    },
    "16": {
      "js": [
        {
          "file": "assets/js/16.a64dd3e8.js",
          "hash": "a10810661d8ffd81d403",
          "publicPath": "/site/assets/js/16.a64dd3e8.js"
        }
      ]
    },
    "26": {
      "js": [
        {
          "file": "assets/js/7199ad53.090e055e.js",
          "hash": "368b22d60596f38071ca",
          "publicPath": "/site/assets/js/7199ad53.090e055e.js"
        }
      ]
    },
    "35": {
      "js": [
        {
          "file": "assets/js/8e9f0a8a.01216480.js",
          "hash": "ac7013f33c3c12ba9e7e",
          "publicPath": "/site/assets/js/8e9f0a8a.01216480.js"
        }
      ]
    },
    "53": {
      "js": [
        {
          "file": "assets/js/935f2afb.368a267f.js",
          "hash": "6239763e8e322464ad67",
          "publicPath": "/site/assets/js/935f2afb.368a267f.js"
        }
      ]
    },
    "61": {
      "js": [
        {
          "file": "assets/js/2868cdab.9b703de2.js",
          "hash": "c8890b3aa3df67f8ac64",
          "publicPath": "/site/assets/js/2868cdab.9b703de2.js"
        }
      ]
    },
    "80": {
      "js": [
        {
          "file": "assets/js/e268232c.6bfc2272.js",
          "hash": "56fb841bd06ffe014fb7",
          "publicPath": "/site/assets/js/e268232c.6bfc2272.js"
        }
      ]
    },
    "83": {
      "js": [
        {
          "file": "assets/js/32dd35a8.153c6686.js",
          "hash": "f1f10e1f3ecaa7bc9775",
          "publicPath": "/site/assets/js/32dd35a8.153c6686.js"
        }
      ]
    },
    "85": {
      "js": [
        {
          "file": "assets/js/1f391b9e.43dc294a.js",
          "hash": "7bd6c7c2a07fe0eb9226",
          "publicPath": "/site/assets/js/1f391b9e.43dc294a.js"
        }
      ]
    },
    "89": {
      "js": [
        {
          "file": "assets/js/a6aa9e1f.6889f836.js",
          "hash": "340d32104cd5aa3c4d9c",
          "publicPath": "/site/assets/js/a6aa9e1f.6889f836.js"
        }
      ]
    },
    "103": {
      "js": [
        {
          "file": "assets/js/ccc49370.ad1ccce5.js",
          "hash": "c7569721d19cf06daef6",
          "publicPath": "/site/assets/js/ccc49370.ad1ccce5.js"
        }
      ]
    },
    "151": {
      "js": [
        {
          "file": "assets/js/b99c8c1f.a618c522.js",
          "hash": "cdc482e142ff1d5a2adb",
          "publicPath": "/site/assets/js/b99c8c1f.a618c522.js"
        }
      ]
    },
    "176": {
      "js": [
        {
          "file": "assets/js/d610846f.50e3fcbc.js",
          "hash": "f095af9e0a017e5fe6f5",
          "publicPath": "/site/assets/js/d610846f.50e3fcbc.js"
        }
      ]
    },
    "179": {
      "js": [
        {
          "file": "assets/js/main.8a68728b.js",
          "hash": "7d6874e37a0acf064e4b",
          "publicPath": "/site/assets/js/main.8a68728b.js"
        }
      ]
    },
    "195": {
      "js": [
        {
          "file": "assets/js/c4f5d8e4.191f85bd.js",
          "hash": "d38edb125f97ff408ad6",
          "publicPath": "/site/assets/js/c4f5d8e4.191f85bd.js"
        }
      ]
    },
    "226": {
      "js": [
        {
          "file": "assets/js/5c2d8334.a25cdf63.js",
          "hash": "9255886d9438de446226",
          "publicPath": "/site/assets/js/5c2d8334.a25cdf63.js"
        }
      ]
    },
    "246": {
      "js": [
        {
          "file": "assets/js/c890ceb5.c468cca3.js",
          "hash": "82d6d651f722dce80a3f",
          "publicPath": "/site/assets/js/c890ceb5.c468cca3.js"
        }
      ]
    },
    "264": {
      "js": [
        {
          "file": "assets/js/f05443a6.bf5bc8ff.js",
          "hash": "ad960d442f823da4edc0",
          "publicPath": "/site/assets/js/f05443a6.bf5bc8ff.js"
        }
      ]
    },
    "277": {
      "js": [
        {
          "file": "assets/js/277.045fee86.js",
          "hash": "5af212a51b8481cca70f",
          "publicPath": "/site/assets/js/277.045fee86.js"
        }
      ]
    },
    "303": {
      "js": [
        {
          "file": "assets/js/runtime~main.92936e70.js",
          "hash": "26f19ac91234151606ab",
          "publicPath": "/site/assets/js/runtime~main.92936e70.js"
        }
      ]
    },
    "414": {
      "js": [
        {
          "file": "assets/js/393be207.fffa94b2.js",
          "hash": "59a99462f5b031c9a050",
          "publicPath": "/site/assets/js/393be207.fffa94b2.js"
        }
      ]
    },
    "447": {
      "js": [
        {
          "file": "assets/js/ab8db3b5.c60c798c.js",
          "hash": "0b6a56a031d900768081",
          "publicPath": "/site/assets/js/ab8db3b5.c60c798c.js"
        }
      ]
    },
    "449": {
      "js": [
        {
          "file": "assets/js/af172acd.86de70f2.js",
          "hash": "8db6dab898a0f043b0c9",
          "publicPath": "/site/assets/js/af172acd.86de70f2.js"
        }
      ]
    },
    "532": {
      "css": [
        {
          "file": "assets/css/styles.aa76a78f.css",
          "hash": "d5f89a4ead914b6a9d73",
          "publicPath": "/site/assets/css/styles.aa76a78f.css"
        }
      ]
    },
    "535": {
      "js": [
        {
          "file": "assets/js/814f3328.917e4e81.js",
          "hash": "cd1691d3638aff36495b",
          "publicPath": "/site/assets/js/814f3328.917e4e81.js"
        }
      ]
    },
    "543": {
      "js": [
        {
          "file": "assets/js/4ad2bd8b.960cb01c.js",
          "hash": "eb8facc86f79971f84e8",
          "publicPath": "/site/assets/js/4ad2bd8b.960cb01c.js"
        }
      ]
    },
    "592": {
      "js": [
        {
          "file": "assets/js/common.3ecd68f2.js",
          "hash": "39f2b331590d197e313e",
          "publicPath": "/site/assets/js/common.3ecd68f2.js"
        }
      ]
    },
    "608": {
      "js": [
        {
          "file": "assets/js/608.32e04694.js",
          "hash": "6e48747b42370733e059",
          "publicPath": "/site/assets/js/608.32e04694.js"
        },
        {
          "file": "assets/js/1be78505.8c5d5367.js",
          "hash": "024e317cebe654ec2a96",
          "publicPath": "/site/assets/js/1be78505.8c5d5367.js"
        }
      ]
    },
    "610": {
      "js": [
        {
          "file": "assets/js/6875c492.6bdd3dd2.js",
          "hash": "af3de3b02efde327c88a",
          "publicPath": "/site/assets/js/6875c492.6bdd3dd2.js"
        }
      ]
    },
    "639": {
      "js": [
        {
          "file": "assets/js/3f722a97.74da33e6.js",
          "hash": "dc6e6f72c38cfdf09e1c",
          "publicPath": "/site/assets/js/3f722a97.74da33e6.js"
        }
      ]
    },
    "671": {
      "js": [
        {
          "file": "assets/js/0e384e19.9e7b02ae.js",
          "hash": "5f5d8ae967d1b419e4fc",
          "publicPath": "/site/assets/js/0e384e19.9e7b02ae.js"
        }
      ]
    },
    "676": {
      "js": [
        {
          "file": "assets/js/8c484570.68af9761.js",
          "hash": "5e4d2c5ecf64ac1a2520",
          "publicPath": "/site/assets/js/8c484570.68af9761.js"
        }
      ]
    },
    "694": {
      "js": [
        {
          "file": "assets/js/bdd709f1.05f449d6.js",
          "hash": "768d1507a7721e5ca225",
          "publicPath": "/site/assets/js/bdd709f1.05f449d6.js"
        }
      ]
    },
    "707": {
      "js": [
        {
          "file": "assets/js/3570154c.ae79e79d.js",
          "hash": "5c2005abeb3b8f507987",
          "publicPath": "/site/assets/js/3570154c.ae79e79d.js"
        }
      ]
    },
    "743": {
      "js": [
        {
          "file": "assets/js/f8551aab.e2840020.js",
          "hash": "7a0c15da517424dee019",
          "publicPath": "/site/assets/js/f8551aab.e2840020.js"
        }
      ]
    },
    "869": {
      "js": [
        {
          "file": "assets/js/a0632b58.d854e6d5.js",
          "hash": "332aeee45e0d9505088d",
          "publicPath": "/site/assets/js/a0632b58.d854e6d5.js"
        }
      ]
    },
    "918": {
      "js": [
        {
          "file": "assets/js/17896441.80295196.js",
          "hash": "f784e50c56e77704432b",
          "publicPath": "/site/assets/js/17896441.80295196.js"
        }
      ]
    }
  }
}